brains.py
setup.py
brains.egg-info/PKG-INFO
brains.egg-info/SOURCES.txt
brains.egg-info/dependency_links.txt
brains.egg-info/entry_points.txt
brains.egg-info/requires.txt
brains.egg-info/top_level.txt