Metadata-Version: 1.1
Name: brains
Version: 0.0.5
Summary: Helps submit files to brains app
Home-page: https://github.com/dev-coop/brains-cli
Author: Eric Carmichael
Author-email: eric@ckcollab.com
License: MIT
Platform: UNKNOWN
Classifier: Intended Audience :: Developers
Classifier: Natural Language :: English
Classifier: License :: OSI Approved :: MIT License
Classifier: Programming Language :: Python
Classifier: Programming Language :: Python :: 2
Classifier: Programming Language :: Python :: 2.6
Classifier: Programming Language :: Python :: 2.7
Classifier: Topic :: Software Development :: Libraries :: Python Modules
